{
  "schemaVersion": 2,
  "id": "common-ground-district",
  "name": "Common Ground District · Facilities Plan",
  "world": { "width": 240, "height": 360, "unit": "m", "grid": 1 },
  "simulation": {
    "buildingMappings": {
      "culture_reading_building_01": "cultural",
      "food_building_01": "dining",
      "central_park_01": "central-park",
      "central_plaza_01": "night-market",
      "multipurpose_event_center_01": "performance",
      "bar_building_01": "bar",
      "game_entertainment_building_01": "entertainment",
      "sports_building_01": "sports",
      "night_school_building_01": "night-school"
    },
    "displayOnlyObjectIds": ["central-park-south"]
  },
  "layers": [
    { "id": "ground", "z": 0, "locked": true },
    { "id": "infrastructure", "z": 10, "locked": false },
    { "id": "venues", "z": 20, "locked": false },
    { "id": "decor", "z": 30, "locked": false }
  ],
  "objects": [
    { "id": "road-north", "layer": "infrastructure", "kind": "road", "variant": "horizontal", "x": 16, "y": 18, "width": 208, "height": 10, "rotation": 0, "z": 5 },
    { "id": "road-south", "layer": "infrastructure", "kind": "road", "variant": "horizontal", "x": 16, "y": 330, "width": 208, "height": 10, "rotation": 0, "z": 5 },
    { "id": "road-west", "layer": "infrastructure", "kind": "road", "variant": "vertical", "x": 24, "y": 18, "width": 10, "height": 322, "rotation": 0, "z": 5 },
    { "id": "road-east", "layer": "infrastructure", "kind": "road", "variant": "vertical", "x": 206, "y": 18, "width": 10, "height": 322, "rotation": 0, "z": 5 },
    { "id": "road-north-cross", "layer": "infrastructure", "kind": "road", "variant": "horizontal", "x": 28, "y": 150, "width": 184, "height": 8, "rotation": 0, "z": 5 },
    { "id": "road-central-cross", "layer": "infrastructure", "kind": "road", "variant": "horizontal", "x": 28, "y": 218, "width": 184, "height": 8, "rotation": 0, "z": 5 },
    { "id": "road-west-spur", "layer": "infrastructure", "kind": "road", "variant": "vertical", "x": 93, "y": 28, "width": 7, "height": 122, "rotation": 0, "z": 5 },
    { "id": "road-east-spur", "layer": "infrastructure", "kind": "road", "variant": "vertical", "x": 148, "y": 157, "width": 7, "height": 173, "rotation": 0, "z": 5 },

    { "id": "crosswalk-west-north", "layer": "infrastructure", "kind": "crosswalk", "variant": "horizontal", "x": 22, "y": 151, "width": 14, "height": 5, "rotation": 0, "z": 7 },
    { "id": "crosswalk-east-north", "layer": "infrastructure", "kind": "crosswalk", "variant": "horizontal", "x": 204, "y": 151, "width": 14, "height": 5, "rotation": 0, "z": 7 },
    { "id": "crosswalk-west-central", "layer": "infrastructure", "kind": "crosswalk", "variant": "horizontal", "x": 22, "y": 219, "width": 14, "height": 5, "rotation": 0, "z": 7 },
    { "id": "crosswalk-east-central", "layer": "infrastructure", "kind": "crosswalk", "variant": "horizontal", "x": 204, "y": 219, "width": 14, "height": 5, "rotation": 0, "z": 7 },

    { "id": "central-park", "layer": "venues", "kind": "venue", "variant": "central-park", "x": 39, "y": 36, "width": 58, "height": 112, "rotation": 0, "z": 2, "shape": { "type": "rect" }, "label": { "zh": "中央社区公园", "en": "CENTRAL COMMUNITY PARK" } },
    { "id": "performance", "layer": "venues", "kind": "venue", "variant": "performance", "x": 108, "y": 35, "width": 84, "height": 72, "rotation": 0, "z": 3, "shape": { "type": "polygon", "points": [[16, 0], [84, 0], [100, 20], [100, 80], [84, 100], [16, 100], [0, 80], [0, 20]] }, "label": { "zh": "社区体育与演艺中心", "en": "SPORTS + PERFORMANCE" } },
    { "id": "sports", "layer": "venues", "kind": "venue", "variant": "sports", "x": 121, "y": 113, "width": 66, "height": 31, "rotation": 0, "z": 3, "shape": { "type": "rect" }, "label": { "zh": "社区运动馆", "en": "COMMUNITY SPORTS" } },
    { "id": "entertainment", "layer": "venues", "kind": "venue", "variant": "entertainment", "x": 49, "y": 72, "width": 34, "height": 64, "rotation": 0, "z": 4, "shape": { "type": "rect" }, "label": { "zh": "游戏娱乐中心", "en": "GAMES + ENTERTAINMENT" } },
    { "id": "bar", "layer": "venues", "kind": "venue", "variant": "bar", "x": 48, "y": 172, "width": 35, "height": 47, "rotation": 0, "z": 3, "shape": { "type": "rect" }, "label": { "zh": "夜生活与酒吧", "en": "NIGHTLIFE + BAR" } },
    { "id": "night-market", "layer": "venues", "kind": "venue", "variant": "night-market", "x": 85, "y": 168, "width": 56, "height": 153, "rotation": 0, "z": 2, "shape": { "type": "polygon", "points": [[22, 0], [72, 0], [100, 17], [100, 83], [74, 100], [27, 100], [0, 83], [0, 20]] }, "label": { "zh": "中央社区广场", "en": "CENTRAL COMMUNITY PLAZA" } },
    { "id": "cultural", "layer": "venues", "kind": "venue", "variant": "cultural", "x": 158, "y": 166, "width": 40, "height": 46, "rotation": 0, "z": 3, "shape": { "type": "rect" }, "label": { "zh": "文化阅读中心", "en": "CULTURE + READING" } },
    { "id": "night-school", "layer": "venues", "kind": "venue", "variant": "night-school", "x": 164, "y": 235, "width": 39, "height": 74, "rotation": 0, "z": 3, "shape": { "type": "rect" }, "label": { "zh": "夜校与兴趣学习", "en": "NIGHT SCHOOL + INTERESTS" } },
    { "id": "dining", "layer": "venues", "kind": "venue", "variant": "dining", "x": 48, "y": 250, "width": 41, "height": 57, "rotation": 0, "z": 3, "shape": { "type": "rect" }, "label": { "zh": "餐饮社交中心", "en": "FOOD + BEVERAGE" } },
    { "id": "central-park-south", "layer": "venues", "kind": "venue", "variant": "central-park", "x": 141, "y": 242, "width": 20, "height": 68, "rotation": 0, "z": 1, "shape": { "type": "rect" }, "label": { "zh": "中央社区公园南园", "en": "SOUTH PARK" } },

    { "id": "trees-north-park", "layer": "decor", "kind": "decor", "variant": "tree-row", "x": 38, "y": 38, "width": 58, "height": 5, "rotation": 0, "z": 6 },
    { "id": "trees-west-edge", "layer": "decor", "kind": "decor", "variant": "tree-row", "x": 36, "y": 45, "width": 5, "height": 264, "rotation": 90, "z": 6 },
    { "id": "trees-east-edge", "layer": "decor", "kind": "decor", "variant": "tree-row", "x": 199, "y": 43, "width": 5, "height": 270, "rotation": 90, "z": 6 },
    { "id": "trees-south-park", "layer": "decor", "kind": "decor", "variant": "tree-row", "x": 140, "y": 305, "width": 22, "height": 5, "rotation": 0, "z": 6 },
    { "id": "plaza-fountain", "layer": "decor", "kind": "decor", "variant": "fountain", "x": 108, "y": 217, "width": 10, "height": 10, "rotation": 0, "z": 7 },
    { "id": "plaza-market-tables", "layer": "decor", "kind": "decor", "variant": "market-tables", "x": 99, "y": 265, "width": 28, "height": 22, "rotation": 0, "z": 7 }
  ]
}
